README.md
setup.py
halfbakery_driver/__init__.py
halfbakery_driver/api.py
halfbakery_driver/test_.py
halfbakery_driver/utils.py
halfbakery_driver.egg-info/PKG-INFO
halfbakery_driver.egg-info/SOURCES.txt
halfbakery_driver.egg-info/dependency_links.txt
halfbakery_driver.egg-info/not-zip-safe
halfbakery_driver.egg-info/requires.txt
halfbakery_driver.egg-info/top_level.txt