Metadata-Version: 2.1
Name: halfbakery-driver
Version: 0.1.1
Summary: Halfbakery communal database controller.
Home-page: https://github.com/drivernet/halfbakery-driver
Author: Mindey
Author-email: mindey@wefindx.com
License: PUBLIC BENEFIT
Platform: UNKNOWN
Provides-Extra: test
